socionics/__init__.py
socionics/core.py
socionics-1.0.dist-info/DESCRIPTION.rst
socionics-1.0.dist-info/METADATA
socionics-1.0.dist-info/RECORD
socionics-1.0.dist-info/WHEEL
socionics-1.0.dist-info/metadata.json
socionics-1.0.dist-info/top_level.txt
