Metadata-Version: 2.0
Name: socionics
Version: 1.0
Summary: Socionics module
Home-page: UNKNOWN
Author: MyrikLD
Author-email: myrik260138@tut.by
License: GPLv3
Keywords: соционика,socionics,соционический,socionica,socionic
Platform: UNKNOWN
